<?xml version="1.0" encoding="utf-8" standalone="yes" ?>
<ResultSet xmlns:xsi="http://www.w3.org/2001/XMLSchema-instance" xmlns="urn:yahoo:answers" xsi:schemaLocation="urn:yahoo:answers http://answers.yahooapis.com/AnswersService/V1/AnswerResponse.xsd">
  <Question id="20100320061101AAgtAcK" type="Answered">
    <Subject>is mobile broadband any good?</Subject>
    <Content>My contract ends with AOL next week and I really want a new laptop but can;t afford one at the moment so was thinking about mobile broadband with a free laptop in the offer. But my mate has T-Mobile and it&#039;s a nightmare, the pictures are of very poor quality and it&#039;s sooo slowly and so bad I&#039;d rather have no internet at all. Just wondering if any of them networks are better or even better than home broadband. 

Thanx :)
</Content>
    <Date>2010-03-20 06:11:01</Date>
    <Timestamp>1269090661</Timestamp>
    <Link>http://answers.yahoo.com/question/?qid=20100320061101AAgtAcK</Link>
    <Category id="2115500139">Other - Internet</Category>
    <UserId>Wmg651Wpaa</UserId>
    <UserNick>Thomas D</UserNick>
    <UserPhotoURL>http://l.yimg.com/a/i/identity/nopic_48.gif</UserPhotoURL>
    <NumAnswers>6</NumAnswers>
    <NumComments>0</NumComments>
    <ChosenAnswer>if you are always on-the-go and not a heavy internet user, you can use mobile broadband. but wired internet connection is still faster than wireless.</ChosenAnswer>
    <ChosenAnswererId>AA10365695</ChosenAnswererId>
    <ChosenAnswererNick>eric_12</ChosenAnswererNick>
    <ChosenAnswerTimestamp>1269092275</ChosenAnswerTimestamp>
    <ChosenAnswerAwardTimestamp>1269185994</ChosenAnswerAwardTimestamp>
    <Answers>
        <Answer>
            <Content>Try Cricket it&#039;s only $40 a month
It&#039;s a lot better than T-mobile &amp; cheaper</Content>
            <Reference></Reference>
            <Best></Best>
            <UserId>UnKvHJt2aa</UserId>
            <UserNick>molly</UserNick>
            <Date>2010-03-20 06:13:39</Date>
            <Timestamp>1269090819</Timestamp>
        </Answer>
        <Answer>
            <Content>I can watch streaming video (YouTube, MySpace etc.) smoothly with mobile broadband.
Assuming you&#039;re in the UK, check Vodafone out as their monthly plan offers a mobile broadband speed double any of the others and double the speed of any prepay mobile broadband</Content>
            <Reference></Reference>
            <Best></Best>
            <UserId>2LbTrlQnaa</UserId>
            <UserNick>JIM</UserNick>
            <Date>2010-03-20 06:14:54</Date>
            <Timestamp>1269090894</Timestamp>
        </Answer>
        <Answer>
            <Content>Wired is still cheaper and faster (Comcast, Etc.).

Image quality won&#039;t be affected by mobile but it will be slower (It will be hard to play multiplayer games online). 

I wouldn&#039;t recommend mobile broadband as a replacement for home highspeed unless you travel a lot and need internet everywhere.</Content>
            <Reference>http://techgeeks-online.com/support/</Reference>
            <Best></Best>
            <UserId>BzW3tAnBaa</UserId>
            <UserNick>TechGeek</UserNick>
            <Date>2010-03-20 06:15:48</Date>
            <Timestamp>1269090948</Timestamp>
        </Answer>
        <Answer>
            <Content>Are you in the UK?

If so, go for 3 network. I use it. You actually get free broadband for a year, you top-up like you would a mobile phone [it has a sim card] and you can send texts on it. It has fast connection.

X</Content>
            <Reference></Reference>
            <Best></Best>
            <UserId>jglcaLu1aa</UserId>
            <UserNick>Ali rit de votre immaturité</UserNick>
            <Date>2010-03-20 06:18:06</Date>
            <Timestamp>1269091086</Timestamp>
        </Answer>
        <Answer>
            <Content>if you are always on-the-go and not a heavy internet user, you can use mobile broadband. but wired internet connection is still faster than wireless.</Content>
            <Reference></Reference>
            <Best>3</Best>
            <UserId>AA10365695</UserId>
            <UserNick>eric_12</UserNick>
            <Date>2010-03-20 06:37:55</Date>
            <Timestamp>1269092275</Timestamp>
        </Answer>
        <Answer>
            <Content>the O2 one is not to bad at all!</Content>
            <Reference></Reference>
            <Best></Best>
            <UserId>6COAsT9caa</UserId>
            <UserNick>Fifi</UserNick>
            <Date>2010-03-20 06:48:35</Date>
            <Timestamp>1269092915</Timestamp>
        </Answer>
    </Answers>
    <Comments>
    </Comments>
  </Question>
</ResultSet>
<!-- ws10.ydn.gq1.yahoo.com uncompressed/chunked Tue Apr  6 20:32:04 PDT 2010 -->
