<?xml version="1.0" encoding="utf-8" standalone="yes" ?>
<ResultSet xmlns:xsi="http://www.w3.org/2001/XMLSchema-instance" xmlns="urn:yahoo:answers" xsi:schemaLocation="urn:yahoo:answers http://answers.yahooapis.com/AnswersService/V1/AnswerResponse.xsd">
  <Question id="20100321144632AAGHr0i" type="Answered">
    <Subject>Return Policy on Amazon UK?</Subject>
    <Content>I got the product wrapped in bubble wrap in an envelope and I want to return it (it has corrupt data) but the Amazon return policy says that it must be returned in the packaging it came in. Of course, I threw recycled the envelope and threw away the bubble wrap as I thought they were rubbish. Will I have to sift through my rubbish to re-wrap it in the bubble wrap/envelope it came in?

Thanks ☺
</Content>
    <Date>2010-03-21 14:46:32</Date>
    <Timestamp>1269207992</Timestamp>
    <Link>http://answers.yahoo.com/question/?qid=20100321144632AAGHr0i</Link>
    <Category id="2115500139">Other - Internet</Category>
    <UserId>rQEJATQgaa</UserId>
    <UserNick>lcjj7</UserNick>
    <UserPhotoURL></UserPhotoURL>
    <NumAnswers>1</NumAnswers>
    <NumComments>0</NumComments>
    <ChosenAnswer>yes. and &quot;threw recycled&quot;?. methinks you tried to re-write that. get your hands in that bin Jackman</ChosenAnswer>
    <ChosenAnswererId>e5ea1441af58fc140a14780db43063a4aa</ChosenAnswererId>
    <ChosenAnswererNick>Hodgie</ChosenAnswererNick>
    <ChosenAnswerTimestamp>1269208430</ChosenAnswerTimestamp>
    <ChosenAnswerAwardTimestamp>1269727532</ChosenAnswerAwardTimestamp>
    <Answers>
        <Answer>
            <Content>yes. and &quot;threw recycled&quot;?. methinks you tried to re-write that. get your hands in that bin Jackman</Content>
            <Reference></Reference>
            <Best>5</Best>
            <UserId>e5ea1441af58fc140a14780db43063a4aa</UserId>
            <UserNick>Hodgie</UserNick>
            <Date>2010-03-21 14:53:50</Date>
            <Timestamp>1269208430</Timestamp>
        </Answer>
    </Answers>
    <Comments>
    </Comments>
  </Question>
</ResultSet>
<!-- ws10.ydn.gq1.yahoo.com uncompressed/chunked Tue Apr  6 20:26:20 PDT 2010 -->
