<?xml version="1.0" encoding="utf-8" standalone="yes" ?>
<ResultSet xmlns:xsi="http://www.w3.org/2001/XMLSchema-instance" xmlns="urn:yahoo:answers" xsi:schemaLocation="urn:yahoo:answers http://answers.yahooapis.com/AnswersService/V1/AnswerResponse.xsd">
  <Question id="20100318145033AAS9GA4" type="Answered">
    <Subject>About how long until my order arrives at Walmart once it has been shipped?</Subject>
    <Content>Yesterday it said it had shipped. I know it says 7-10 business days. But what are your experiences? Has an order ever came early for you?
Thanks!
</Content>
    <Date>2010-03-18 14:50:33</Date>
    <Timestamp>1268949033</Timestamp>
    <Link>http://answers.yahoo.com/question/?qid=20100318145033AAS9GA4</Link>
    <Category id="2115500139">Other - Internet</Category>
    <UserId>xAnqehXWaa</UserId>
    <UserNick>fullyxalive</UserNick>
    <UserPhotoURL>http://avatars.zenfs.com/users/19s-CrGScAAIB34TFHEebCmEB.medium.png</UserPhotoURL>
    <NumAnswers>2</NumAnswers>
    <NumComments>0</NumComments>
    <ChosenAnswer>do not plan on their time being the actual time . I have waited for 3 weeks  before .</ChosenAnswer>
    <ChosenAnswererId>u2w40ptEaa</ChosenAnswererId>
    <ChosenAnswererNick>marcus</ChosenAnswererNick>
    <ChosenAnswerTimestamp>1268949294</ChosenAnswerTimestamp>
    <ChosenAnswerAwardTimestamp>1269468325</ChosenAnswerAwardTimestamp>
    <Answers>
        <Answer>
            <Content>do not plan on their time being the actual time . I have waited for 3 weeks  before .</Content>
            <Reference></Reference>
            <Best>5</Best>
            <UserId>u2w40ptEaa</UserId>
            <UserNick>marcus</UserNick>
            <Date>2010-03-18 14:54:54</Date>
            <Timestamp>1268949294</Timestamp>
        </Answer>
        <Answer>
            <Content>Yeah, usually 7-10 Business Days.</Content>
            <Reference></Reference>
            <Best></Best>
            <UserId>OlT5sWCkaa</UserId>
            <UserNick>Nora</UserNick>
            <Date>2010-03-18 15:03:28</Date>
            <Timestamp>1268949808</Timestamp>
        </Answer>
    </Answers>
    <Comments>
    </Comments>
  </Question>
</ResultSet>
<!-- ws12.ydn.gq1.yahoo.com uncompressed/chunked Tue Apr  6 20:38:43 PDT 2010 -->
