<?xml version="1.0" encoding="utf-8" standalone="yes" ?>
<ResultSet xmlns:xsi="http://www.w3.org/2001/XMLSchema-instance" xmlns="urn:yahoo:answers" xsi:schemaLocation="urn:yahoo:answers http://answers.yahooapis.com/AnswersService/V1/AnswerResponse.xsd">
  <Question id="20100224134258AAnNTUw" type="Answered">
    <Subject>Where&#039;s the best place to sell DVDs online?</Subject>
    <Content>My dad wants me to sell two larger products for him on Ebay. He and I also have a few DVDs we want to sell. Is Ebay the best (or good enough) place? Or is there another site that&#039;s better to sell DVDs at? (I also have box seasons of TV shows.)
</Content>
    <Date>2010-02-24 13:42:58</Date>
    <Timestamp>1267047778</Timestamp>
    <Link>http://answers.yahoo.com/question/?qid=20100224134258AAnNTUw</Link>
    <Category id="2115500139">Other - Internet</Category>
    <UserId>I5EIj4xLaa</UserId>
    <UserNick>twins1729</UserNick>
    <UserPhotoURL>http://a323.yahoofs.com/coreid/4b64f340i7e7zul4re4/.qZqAhwlbK8LhY0a3UlneLI-/1/tn48.jpg?ciAAToMBLwI5_J7q</UserPhotoURL>
    <NumAnswers>3</NumAnswers>
    <NumComments>0</NumComments>
    <ChosenAnswer>You can also try Amazon marketplace</ChosenAnswer>
    <ChosenAnswererId>787d430baebe2f42e01bae57315dca4daa</ChosenAnswererId>
    <ChosenAnswererNick>the swines!</ChosenAnswererNick>
    <ChosenAnswerTimestamp>1267047908</ChosenAnswerTimestamp>
    <ChosenAnswerAwardTimestamp>1267717393</ChosenAnswerAwardTimestamp>
    <Answers>
        <Answer>
            <Content>i sell a good chunk of my things on craigslist.org</Content>
            <Reference></Reference>
            <Best></Best>
            <UserId>V5oo4ns0aa</UserId>
            <UserNick>kyle</UserNick>
            <Date>2010-02-24 13:44:39</Date>
            <Timestamp>1267047879</Timestamp>
        </Answer>
        <Answer>
            <Content>You can also try Amazon marketplace</Content>
            <Reference></Reference>
            <Best>5</Best>
            <UserId>787d430baebe2f42e01bae57315dca4daa</UserId>
            <UserNick>the swines!</UserNick>
            <Date>2010-02-24 13:45:08</Date>
            <Timestamp>1267047908</Timestamp>
        </Answer>
        <Answer>
            <Content>ebay and amazon they charge you fee, but craiglists.org if free, avoid scam do local only, do not accept wire xfers.</Content>
            <Reference></Reference>
            <Best></Best>
            <UserId>oXXc2LmNaa</UserId>
            <UserNick>John S</UserNick>
            <Date>2010-02-24 13:46:46</Date>
            <Timestamp>1267048006</Timestamp>
        </Answer>
    </Answers>
    <Comments>
    </Comments>
  </Question>
</ResultSet>
<!-- ws09.ydn.gq1.yahoo.com uncompressed/chunked Wed Apr  7 02:13:39 PDT 2010 -->
