<?xml version="1.0" encoding="utf-8" standalone="yes" ?>
<ResultSet xmlns:xsi="http://www.w3.org/2001/XMLSchema-instance" xmlns="urn:yahoo:answers" xsi:schemaLocation="urn:yahoo:answers http://answers.yahooapis.com/AnswersService/V1/AnswerResponse.xsd">
  <Question id="20100228163425AAfhdSD" type="Answered">
    <Subject>Twitter via text message?</Subject>
    <Content>Help! How can I find the phone number to text for Twitter? I&#039;ve been trying to twitter via texting, but I can&#039;t find it anywhere! If anyone has this set up, (For free), can they help me figure it out? *Also, does Verizon allow that for free?*
</Content>
    <Date>2010-02-28 16:34:25</Date>
    <Timestamp>1267403665</Timestamp>
    <Link>http://answers.yahoo.com/question/?qid=20100228163425AAfhdSD</Link>
    <Category id="2115500139">Other - Internet</Category>
    <UserId>jr5s82m2aa</UserId>
    <UserNick>Lewis</UserNick>
    <UserPhotoURL>http://l.yimg.com/q/users/1ZwhrvpS0AAED_CGBXKCZpPfMYro9w3QY.medium.jpg</UserPhotoURL>
    <NumAnswers>1</NumAnswers>
    <NumComments>0</NumComments>
    <ChosenAnswer>You need to register your phone online and then i think the short code that you text to is 40404..  i used to do this on my old phone before i got the droid..  and the texts will come out of your monthly allowance, whatever that may be..</ChosenAnswer>
    <ChosenAnswererId>AA12091609</ChosenAnswererId>
    <ChosenAnswererNick>Nathan</ChosenAnswererNick>
    <ChosenAnswerTimestamp>1267404082</ChosenAnswerTimestamp>
    <ChosenAnswerAwardTimestamp>1267923297</ChosenAnswerAwardTimestamp>
    <Answers>
        <Answer>
            <Content>You need to register your phone online and then i think the short code that you text to is 40404..  i used to do this on my old phone before i got the droid..  and the texts will come out of your monthly allowance, whatever that may be..</Content>
            <Reference>VZW employee- hope it helps- msg me w/ questions :)</Reference>
            <Best>5</Best>
            <UserId>AA12091609</UserId>
            <UserNick>Nathan A</UserNick>
            <Date>2010-02-28 16:41:22</Date>
            <Timestamp>1267404082</Timestamp>
        </Answer>
    </Answers>
    <Comments>
    </Comments>
  </Question>
</ResultSet>
<!-- ws04.ydn.gq1.yahoo.com uncompressed/chunked Wed Apr  7 01:36:04 PDT 2010 -->
