<?xml version="1.0" encoding="utf-8" standalone="yes" ?>
<ResultSet xmlns:xsi="http://www.w3.org/2001/XMLSchema-instance" xmlns="urn:yahoo:answers" xsi:schemaLocation="urn:yahoo:answers http://answers.yahooapis.com/AnswersService/V1/AnswerResponse.xsd">
  <Question id="20100320060108AAAe4A5" type="Answered">
    <Subject>what is it I need to know about points?</Subject>
    <Content>I had answered some questions and it says that I need 127 points to get to level two. I got 127 yesterday and I am still on level one. I logged on today and got four points so I have 131 points but it said today that I had to get 119 points to get to level two, does a couple of days before it says level two and has this happened to you and now I have 126 points, help?
</Content>
    <Date>2010-03-20 06:01:08</Date>
    <Timestamp>1269090068</Timestamp>
    <Link>http://answers.yahoo.com/question/?qid=20100320060108AAAe4A5</Link>
    <Category id="2115500139">Other - Internet</Category>
    <UserId>rNbDRXQGaa</UserId>
    <UserNick>Sj</UserNick>
    <UserPhotoURL>http://l.yimg.com/a/i/identity/nopic_48.gif</UserPhotoURL>
    <NumAnswers>1</NumAnswers>
    <NumComments>0</NumComments>
    <ChosenAnswer>you need 124 MORE points, so add that to your current pointage

You need a total of 250 points to get to level 2</ChosenAnswer>
    <ChosenAnswererId>ul06EmNTaa</ChosenAnswererId>
    <ChosenAnswererNick>▐▀▀▼▀▀▌ ►ʞɯɐpɐ◄ ▐▄▄▲▄▄▌</ChosenAnswererNick>
    <ChosenAnswerTimestamp>1269090144</ChosenAnswerTimestamp>
    <ChosenAnswerAwardTimestamp>1269212490</ChosenAnswerAwardTimestamp>
    <Answers>
        <Answer>
            <Content>you need 124 MORE points, so add that to your current pointage

You need a total of 250 points to get to level 2</Content>
            <Reference></Reference>
            <Best>3</Best>
            <UserId>ul06EmNTaa</UserId>
            <UserNick>▐▀▀▼▀▀▌ ►ʞɯɐpɐ◄ ▐▄▄▲▄▄▌</UserNick>
            <Date>2010-03-20 06:02:24</Date>
            <Timestamp>1269090144</Timestamp>
        </Answer>
    </Answers>
    <Comments>
    </Comments>
  </Question>
</ResultSet>
<!-- ws06.ydn.gq1.yahoo.com uncompressed/chunked Tue Apr  6 20:32:10 PDT 2010 -->
