<?xml version="1.0" encoding="utf-8" standalone="yes" ?>
<ResultSet xmlns:xsi="http://www.w3.org/2001/XMLSchema-instance" xmlns="urn:yahoo:answers" xsi:schemaLocation="urn:yahoo:answers http://answers.yahooapis.com/AnswersService/V1/AnswerResponse.xsd">
  <Question id="20100316013551AAAV1Q9" type="Answered">
    <Subject>Good websites to buy books from?</Subject>
    <Content>What&#039;s your favourite/recommended book purchasing website?

Thanks in advance :)!
The thing is im scared that if i get books online i will get a bad quality or poor condition one. does it happen on amazon.com?
</Content>
    <Date>2010-03-16 01:35:51</Date>
    <Timestamp>1268728551</Timestamp>
    <Link>http://answers.yahoo.com/question/?qid=20100316013551AAAV1Q9</Link>
    <Category id="2115500139">Other - Internet</Category>
    <UserId>aplNDE3Laa</UserId>
    <UserNick>skittleluver</UserNick>
    <UserPhotoURL>http://l.yimg.com/q/users/1-Cns-Fc9AAECx2Jb0I1uEl0SVR_zlw==.medium.jpg</UserPhotoURL>
    <NumAnswers>7</NumAnswers>
    <NumComments>0</NumComments>
    <ChosenAnswer>I like amazon because they are usually reliable and have pretty good review system to help with purchasing.</ChosenAnswer>
    <ChosenAnswererId>qxR1Zbhpaa</ChosenAnswererId>
    <ChosenAnswererNick>matthewfulfs</ChosenAnswererNick>
    <ChosenAnswerTimestamp>1268728651</ChosenAnswerTimestamp>
    <ChosenAnswerAwardTimestamp>1269065478</ChosenAnswerAwardTimestamp>
    <Answers>
        <Answer>
            <Content>I like amazon because they are usually reliable and have pretty good review system to help with purchasing.</Content>
            <Reference>http://www.amazon.com</Reference>
            <Best>5</Best>
            <UserId>qxR1Zbhpaa</UserId>
            <UserNick>matthewfulfs</UserNick>
            <Date>2010-03-16 01:37:31</Date>
            <Timestamp>1268728651</Timestamp>
        </Answer>
        <Answer>
            <Content>Amazon.com, cheap.</Content>
            <Reference></Reference>
            <Best></Best>
            <UserId>ULw1777caa</UserId>
            <UserNick>jasonicus</UserNick>
            <Date>2010-03-16 01:37:49</Date>
            <Timestamp>1268728669</Timestamp>
        </Answer>
        <Answer>
            <Content>www.clickbank.com  is the best website for purchasing books.</Content>
            <Reference></Reference>
            <Best></Best>
            <UserId>fBhwzKaQaa</UserId>
            <UserNick>Tayyab</UserNick>
            <Date>2010-03-16 01:40:37</Date>
            <Timestamp>1268728837</Timestamp>
        </Answer>
        <Answer>
            <Content>I love dealstudio,it is a good place to buy books, it has all kinds of book and they are very cheap.There are lots of deals.
Here is a great site, you can have a try:http://www.dealstudio.com/searchdeals.php?q=book&amp;type=deal&amp;ru=2770074
Let&#039;s enjoy it togther!
Good luck!</Content>
            <Reference></Reference>
            <Best></Best>
            <UserId>6dBWHgPmaa</UserId>
            <UserNick>bear</UserNick>
            <Date>2010-03-16 01:41:11</Date>
            <Timestamp>1268728871</Timestamp>
        </Answer>
        <Answer>
            <Content>www.flipkart.com</Content>
            <Reference></Reference>
            <Best></Best>
            <UserId>AA11841801</UserId>
            <UserNick>whizkris</UserNick>
            <Date>2010-03-16 03:49:45</Date>
            <Timestamp>1268736585</Timestamp>
        </Answer>
        <Answer>
            <Content>amazon.com and amazon sells new and used books, I have bought books before and that hasn&#039;t happened to me all the books were new and in good condition:)</Content>
            <Reference></Reference>
            <Best></Best>
            <UserId>QaXhloywaa</UserId>
            <UserNick>Arquitect82</UserNick>
            <Date>2010-03-16 13:11:55</Date>
            <Timestamp>1268770315</Timestamp>
        </Answer>
        <Answer>
            <Content>have you tried the library :D
but you cant take out encyclopaedia 
i crack myself up</Content>
            <Reference>your momma</Reference>
            <Best></Best>
            <UserId>paDCCVMdaa</UserId>
            <UserNick>Ciaran</UserNick>
            <Date>2010-03-19 16:19:34</Date>
            <Timestamp>1269040774</Timestamp>
        </Answer>
    </Answers>
    <Comments>
    </Comments>
  </Question>
</ResultSet>
<!-- ws10.ydn.gq1.yahoo.com uncompressed/chunked Tue Apr  6 20:50:36 PDT 2010 -->
