<?xml version="1.0" encoding="utf-8" standalone="yes" ?>
<ResultSet xmlns:xsi="http://www.w3.org/2001/XMLSchema-instance" xmlns="urn:yahoo:answers" xsi:schemaLocation="urn:yahoo:answers http://answers.yahooapis.com/AnswersService/V1/AnswerResponse.xsd">
  <Question id="20100314112910AAZTEiF" type="Answered">
    <Subject>I need a Twitter Username...?</Subject>
    <Content>I can&#039;t think of any. :-\
This is the second time I&#039;ve made a twitter, but I want to create a fresh one.

So can you guys think of any?
ANY that have to do with *rain, music, and/or love*.

I&#039;ve already tried:
peacelovemusic
luvrain
lovepeacemusic
love_music

If it&#039;s really good and I choose it, you get 10 points. :-)
</Content>
    <Date>2010-03-14 11:29:10</Date>
    <Timestamp>1268591350</Timestamp>
    <Link>http://answers.yahoo.com/question/?qid=20100314112910AAZTEiF</Link>
    <Category id="2115500139">Other - Internet</Category>
    <UserId>kjlJFLUJaa</UserId>
    <UserNick>Samantha R</UserNick>
    <UserPhotoURL>http://l.yimg.com/q/users/1Hn0eLuBlAAEC2GKcyKVQxvgA.medium.jpg</UserPhotoURL>
    <NumAnswers>5</NumAnswers>
    <NumComments>0</NumComments>
    <ChosenAnswer>Lovecomedown   :D</ChosenAnswer>
    <ChosenAnswererId>1OQEhkaeaa</ChosenAnswererId>
    <ChosenAnswererNick>garry_welch@rocketmail.com</ChosenAnswererNick>
    <ChosenAnswerTimestamp>1268591830</ChosenAnswerTimestamp>
    <ChosenAnswerAwardTimestamp>1268845295</ChosenAnswerAwardTimestamp>
    <Answers>
        <Answer>
            <Content>Hi You can try  one of these

love4ever
musicwithlove
lovewithmusic
rainylove 
lovesincs
love143</Content>
            <Reference></Reference>
            <Best></Best>
            <UserId>UgcAb9TVaa</UserId>
            <UserNick>ks</UserNick>
            <Date>2010-03-14 11:36:21</Date>
            <Timestamp>1268591781</Timestamp>
        </Answer>
        <Answer>
            <Content>Lovecomedown   :D</Content>
            <Reference></Reference>
            <Best>4</Best>
            <UserId>1OQEhkaeaa</UserId>
            <UserNick>garry_welch@rocketmail.com</UserNick>
            <Date>2010-03-14 11:37:10</Date>
            <Timestamp>1268591830</Timestamp>
        </Answer>
        <Answer>
            <Content>have you tried separating them with periods?
peace.love.music
luv.rain
etc, etc?

rain_peacenlove_music would be my suggestion if not</Content>
            <Reference></Reference>
            <Best></Best>
            <UserId>0e7HLGGuaa</UserId>
            <UserNick>Twinstripes, not Pinstripes!</UserNick>
            <Date>2010-03-14 11:38:11</Date>
            <Timestamp>1268591891</Timestamp>
        </Answer>
        <Answer>
            <Content>How about lesbian mud monkey</Content>
            <Reference></Reference>
            <Best></Best>
            <UserId>5L8NdsPIaa</UserId>
            <UserNick>Rumpel Foreskin</UserNick>
            <Date>2010-03-14 11:41:08</Date>
            <Timestamp>1268592068</Timestamp>
        </Answer>
        <Answer>
            <Content>RainingMusic

You can view private Twitter tweets @ http://viewmorepix.com</Content>
            <Reference></Reference>
            <Best></Best>
            <UserId>X4m2GmP5aa</UserId>
            <UserNick>Red R</UserNick>
            <Date>2010-03-14 12:00:58</Date>
            <Timestamp>1268593258</Timestamp>
        </Answer>
    </Answers>
    <Comments>
    </Comments>
  </Question>
</ResultSet>
<!-- ws10.ydn.gq1.yahoo.com uncompressed/chunked Tue Apr  6 20:59:17 PDT 2010 -->
