<?xml version="1.0" encoding="utf-8" standalone="yes" ?>
<ResultSet xmlns:xsi="http://www.w3.org/2001/XMLSchema-instance" xmlns="urn:yahoo:answers" xsi:schemaLocation="urn:yahoo:answers http://answers.yahooapis.com/AnswersService/V1/AnswerResponse.xsd">
  <Question id="20100319041629AAYRmLO" type="Answered">
    <Subject>Is there any other search engine that is good other than yahoo and google search engines?</Subject>
    <Content>Tell me all u know about search engines

Thank YOU VERY VERY VERY much
</Content>
    <Date>2010-03-19 04:16:29</Date>
    <Timestamp>1268997389</Timestamp>
    <Link>http://answers.yahoo.com/question/?qid=20100319041629AAYRmLO</Link>
    <Category id="2115500139">Other - Internet</Category>
    <UserId>7mRwtSTPaa</UserId>
    <UserNick>.....</UserNick>
    <UserPhotoURL>http://avatars.zenfs.com/users/1_yKICZQVAAEBVIJTiBPpQmU_OA==.medium.png</UserPhotoURL>
    <NumAnswers>4</NumAnswers>
    <NumComments>0</NumComments>
    <ChosenAnswer>Google and Yahoo are the main search engines, but there are other reliable search engines, here is a list of them:
1- www.altavista.com
2- www.AOL.com
3- www.alltheweb.com
4- www.teoma.com
But to get the best results, you need to enhance your query by being as specific as possibly.</ChosenAnswer>
    <ChosenAnswererId>QpkguMpiaa</ChosenAnswererId>
    <ChosenAnswererNick>Alaa</ChosenAnswererNick>
    <ChosenAnswerTimestamp>1268998365</ChosenAnswerTimestamp>
    <ChosenAnswerAwardTimestamp>1269097431</ChosenAnswerAwardTimestamp>
    <Answers>
        <Answer>
            <Content>bing</Content>
            <Reference></Reference>
            <Best></Best>
            <UserId>qOX3EapGaa</UserId>
            <UserNick>Jackie D</UserNick>
            <Date>2010-03-19 04:17:52</Date>
            <Timestamp>1268997472</Timestamp>
        </Answer>
        <Answer>
            <Content>Ask jeeves x</Content>
            <Reference></Reference>
            <Best></Best>
            <UserId>Kps1lAwwaa</UserId>
            <UserNick>Ƹ̵̡Ӝ̵̨̄ƷMaiasMummyƸ̵̡Ӝ̵̨̄Ʒ</UserNick>
            <Date>2010-03-19 04:24:04</Date>
            <Timestamp>1268997844</Timestamp>
        </Answer>
        <Answer>
            <Content>Ask

Bing

Alta vista

Among Meta search engines (the engines which combine search results of 2 or more search engines): Dogpile, meta crawler, excite, leap fish, web crawler...</Content>
            <Reference></Reference>
            <Best></Best>
            <UserId>fmbjJ7lyaa</UserId>
            <UserNick>Cultural Aryan</UserNick>
            <Date>2010-03-19 04:27:53</Date>
            <Timestamp>1268998073</Timestamp>
        </Answer>
        <Answer>
            <Content>Google and Yahoo are the main search engines, but there are other reliable search engines, here is a list of them:
1- www.altavista.com
2- www.AOL.com
3- www.alltheweb.com
4- www.teoma.com
But to get the best results, you need to enhance your query by being as specific as possibly.</Content>
            <Reference>The Big old Web</Reference>
            <Best>3</Best>
            <UserId>QpkguMpiaa</UserId>
            <UserNick>Alaa</UserNick>
            <Date>2010-03-19 04:32:45</Date>
            <Timestamp>1268998365</Timestamp>
        </Answer>
        <Answer>
            <Content>The best search is www.metacrawler.com ---it searches all search engines..http://www.metacrawler.com/</Content>
            <Reference></Reference>
            <Best></Best>
            <UserId>Ln7yu76baa</UserId>
            <UserNick>rilla</UserNick>
            <Date>2010-03-19 04:40:52</Date>
            <Timestamp>1268998852</Timestamp>
        </Answer>
    </Answers>
    <Comments>
    </Comments>
  </Question>
</ResultSet>
<!-- ws09.ydn.gq1.yahoo.com uncompressed/chunked Tue Apr  6 20:36:43 PDT 2010 -->
