<?xml version="1.0" encoding="utf-8" standalone="yes" ?>
<ResultSet xmlns:xsi="http://www.w3.org/2001/XMLSchema-instance" xmlns="urn:yahoo:answers" xsi:schemaLocation="urn:yahoo:answers http://answers.yahooapis.com/AnswersService/V1/AnswerResponse.xsd">
  <Question id="20100226092643AASuXvv" type="Answered">
    <Subject>Why can&#039;t I access ovguide.com?</Subject>
    <Content>I can access all other websites except ovguide.com. Whenever I want to enter the website, there&#039;s always  &quot;problem loading page&quot;. I can access ovguide.com before this without any problems. The &quot;problem loading page&quot; just happened these few weeks. I wonder why.
I want to know how to fix this too.
</Content>
    <Date>2010-02-26 09:26:43</Date>
    <Timestamp>1267205203</Timestamp>
    <Link>http://answers.yahoo.com/question/?qid=20100226092643AASuXvv</Link>
    <Category id="2115500139">Other - Internet</Category>
    <UserId>DanVv1lCaa</UserId>
    <UserNick>StarShine</UserNick>
    <UserPhotoURL>http://l.yimg.com/q/users/1nAXwyyKiAAIBLQE_GIzyiEEjLBsG.medium.jpg</UserPhotoURL>
    <NumAnswers>2</NumAnswers>
    <NumComments>0</NumComments>
    <ChosenAnswer>You should send an email to marketing@ovguide.com with your location and browser version. They will sort you out.

Sorry for the inconvenience.</ChosenAnswer>
    <ChosenAnswererId>GNkVbUooaa</ChosenAnswererId>
    <ChosenAnswererNick>Jason S</ChosenAnswererNick>
    <ChosenAnswerTimestamp>1267230130</ChosenAnswerTimestamp>
    <ChosenAnswerAwardTimestamp>1267278327</ChosenAnswerAwardTimestamp>
    <Answers>
        <Answer>
            <Content>The servers may be down. Or you might have some kind of firewall or internet protection that stops it from loading.</Content>
            <Reference></Reference>
            <Best></Best>
            <UserId>4SfKd4phaa</UserId>
            <UserNick>Adomian</UserNick>
            <Date>2010-02-26 09:31:19</Date>
            <Timestamp>1267205479</Timestamp>
        </Answer>
        <Answer>
            <Content>You should send an email to marketing@ovguide.com with your location and browser version. They will sort you out.

Sorry for the inconvenience.</Content>
            <Reference></Reference>
            <Best>4</Best>
            <UserId>GNkVbUooaa</UserId>
            <UserNick>Jason S</UserNick>
            <Date>2010-02-26 16:22:10</Date>
            <Timestamp>1267230130</Timestamp>
        </Answer>
    </Answers>
    <Comments>
    </Comments>
  </Question>
</ResultSet>
<!-- ws10.ydn.gq1.yahoo.com uncompressed/chunked Wed Apr  7 01:51:19 PDT 2010 -->
